toexe/__init__.py
toexe/toexe.py
toexe-0.1.dist-info/METADATA
toexe-0.1.dist-info/WHEEL
toexe-0.1.dist-info/top_level.txt
toexe-0.1.dist-info/RECORD
