Metadata-Version: 2.1
Name: toexe
Version: 0.1
Summary: A tool for converting Python scripts to EXE files with customizable options
Home-page: https://github.com/yourusername/toexe
Author: Your Name
Author-email: your_email@example.com
Classifier: Programming Language :: Python :: 3
Classifier: License :: OSI Approved :: MIT License
Classifier: Operating System :: OS Independent
Requires-Python: >=3.6
